pantsbuild.pants.contrib.scrooge-1.30.4-py3.6-nspkg.pth
pants/contrib/scrooge/__init__.py
pants/contrib/scrooge/register.py
pants/contrib/scrooge/subsystems/__init__.py
pants/contrib/scrooge/subsystems/scrooge_linter.py
pants/contrib/scrooge/tasks/__init__.py
pants/contrib/scrooge/tasks/java_thrift_library_fingerprint_strategy.py
pants/contrib/scrooge/tasks/scrooge_gen.py
pants/contrib/scrooge/tasks/thrift_linter_task.py
pants/contrib/scrooge/tasks/thrift_util.py
pantsbuild.pants.contrib.scrooge-1.30.4.dist-info/METADATA
pantsbuild.pants.contrib.scrooge-1.30.4.dist-info/RECORD
pantsbuild.pants.contrib.scrooge-1.30.4.dist-info/WHEEL
pantsbuild.pants.contrib.scrooge-1.30.4.dist-info/entry_points.txt
pantsbuild.pants.contrib.scrooge-1.30.4.dist-info/namespace_packages.txt
pantsbuild.pants.contrib.scrooge-1.30.4.dist-info/top_level.txt
pantsbuild.pants.contrib.scrooge-1.30.4.dist-info/zip-safe
